jaxa/README.md
jaxa/__init__.py
jaxa/api/__init__.py
jaxa/api/common/__init__.py
jaxa/api/common/categories.py
jaxa/api/jira/README.md
jaxa/api/jira/__init__.py
jaxa/api/jira/jira_categories.py
jaxa/api/jira/jira_rest_api.py
jaxa/api/rest/__init__.py
jaxa/api/rest/session.py
jaxa/api/xray/__init__.py
jaxa/api/xray/gql_templates/testexecutions/add_testexecutions_to_testplan.graphql
jaxa/api/xray/gql_templates/testexecutions/create_testexecution.graphql
jaxa/api/xray/gql_templates/testexecutions/get_testexecutions_by_jql.graphql
jaxa/api/xray/gql_templates/testplans/assign_tests_to_existing_testplan.graphql
jaxa/api/xray/gql_templates/testplans/create_empty_testplan.graphql
jaxa/api/xray/gql_templates/testplans/create_testplan_with_tests.graphql
jaxa/api/xray/gql_templates/testplans/get_testplan_by_jql.graphql
jaxa/api/xray/gql_templates/testplans/get_testplan_from_id.graphql
jaxa/api/xray/gql_templates/testruns/add_testrun_comment.graphql
jaxa/api/xray/gql_templates/testruns/add_testrun_evidence.graphql
jaxa/api/xray/gql_templates/testruns/get_testruns.graphql
jaxa/api/xray/gql_templates/testruns/get_testruns_by_id.graphql
jaxa/api/xray/gql_templates/testruns/update_testrun_status.graphql
jaxa/api/xray/gql_templates/testruns/update_testrun_timing.graphql
jaxa/api/xray/gql_templates/tests/create_cucumber_test.graphql
jaxa/api/xray/gql_templates/tests/create_generic_test.graphql
jaxa/api/xray/gql_templates/tests/create_manual_test.graphql
jaxa/api/xray/gql_templates/tests/create_maxed_test.graphql
jaxa/api/xray/gql_templates/tests/create_pyautomated_test.graphql
jaxa/api/xray/gql_templates/tests/get_test_by_issue_id.graphql
jaxa/api/xray/gql_templates/tests/get_test_by_jira_id.graphql
jaxa/api/xray/gql_templates/tests/get_test_preconditions_by_test_jira_id.graphql
jaxa/api/xray/gql_templates/tests/get_test_testexecutions_by_test_jira_id.graphql
jaxa/api/xray/gql_templates/tests/get_test_testplans_by_test_jira_id.graphql
jaxa-1.3.0.dist-info/LICENSE
jaxa-1.3.0.dist-info/WHEEL
jaxa-1.3.0.dist-info/entry_points.txt
jaxa-1.3.0.dist-info/METADATA
jaxa-1.3.0.dist-info/RECORD
