Metadata-Version: 2.1
Name: jaxa
Version: 1.3.0
Summary: Jira and Xray API
License: GNU GENERAL PUBLIC LICENSE
Keywords: jira,xray,rest,graphql,api
Author: Gleams API user
Author-email: Stephen.Swannell+ghapi@gmail.com
Requires-Python: >=3.8,<4.0
Classifier: License :: Other/Proprietary License
Classifier: Programming Language :: Python :: 3
Classifier: Programming Language :: Python :: 3.8
Classifier: Programming Language :: Python :: 3.9
Classifier: Programming Language :: Python :: 3.10
Classifier: Programming Language :: Python :: 3.11
Requires-Dist: gql (>=3.4.0,<4.0.0)
Requires-Dist: requests-toolbelt (>=0.10.1)
Requires-Dist: tenacity (>=8.2.2,<9.0.0)
